ff3/__init__.py
ff3/ff3.py
ff3/ff3_test.py
pyfpe_ff3/__init__.py
pyfpe_ff3/ff3.py
pyfpe_ff3/utils.py
pyFPE-0.10.3.dist-info/LICENSE
pyFPE-0.10.3.dist-info/METADATA
pyFPE-0.10.3.dist-info/WHEEL
pyFPE-0.10.3.dist-info/top_level.txt
pyFPE-0.10.3.dist-info/RECORD
