Metadata-Version: 2.1
Name: pyFPE
Version: 0.10.3
Summary: Python FPE- Does Format preserving Encryption of values
Home-page: https://github.com/PuspenduBanerjee/python-fpe
License: MIT license, Apache License
Keywords: python-fpe,pyfpe_ff3,vaultless,tokenization
Platform: UNKNOWN
Classifier: Intended Audience :: Developers
Classifier: License :: OSI Approved :: MIT License
Classifier: License :: OSI Approved :: Apache Software License
Classifier: Natural Language :: English
Classifier: Operating System :: OS Independent
Classifier: Programming Language :: Python :: 3.6
Classifier: Programming Language :: Python :: 3.7
Classifier: Programming Language :: Python :: 3.8
Classifier: Programming Language :: Python :: 3.9
Requires-Python: >=3.5
Requires-Dist: pycryptodome (==3.10.1)
